auto_cert_api/CertbotManager.py
auto_cert_api/Config.py
auto_cert_api/Controller.py
auto_cert_api/Meta.py
auto_cert_api/__init__.py
auto_cert_api/__main__.py
auto_cert_api/Tools/Packages.py
auto_cert_api/Tools/StdOutCapture.py
auto_cert_api/Tools/__init__.py
auto_cert_api-0.3.data/data/auto_cert_api/requirements/all.whl.extra-requirements.txt
auto_cert_api-0.3.data/data/auto_cert_api/requirements/whl.extra-requirements.json
auto_cert_api-0.3.data/data/auto_cert_api/requirements/whl.requirements.txt
auto_cert_api-0.3.dist-info/METADATA
auto_cert_api-0.3.dist-info/WHEEL
auto_cert_api-0.3.dist-info/top_level.txt
auto_cert_api-0.3.dist-info/RECORD
