Metadata-Version: 2.1
Name: auto-cert-api
Version: 0.3
Summary: A tool to automate creation of certbot certificates through a web API.
Home-page: https://gitlab.com/todo
Author: Axel Paccalin
Author-email: axel.paccalin@enno.ai
Project-URL: Bug Tracker, https://gitlab.com/todo/issues
Classifier: Programming Language :: Python :: 3
Classifier: Operating System :: OS Independent
Requires-Python: >=3.8
Requires-Dist: fastapi (==0.85.0)
Requires-Dist: uvicorn (==0.18.3)
Provides-Extra: all
Requires-Dist: certbot-plugin-gandi (==1.3.2) ; extra == 'all'
Requires-Dist: gandi.cli (==1.6) ; extra == 'all'
Requires-Dist: certbot-plugin-ionos (==0.1) ; extra == 'all'
Requires-Dist: ionos-api (==0.1) ; extra == 'all'
Provides-Extra: gandi
Requires-Dist: certbot-plugin-gandi (==1.3.2) ; extra == 'gandi'
Requires-Dist: gandi.cli (==1.6) ; extra == 'gandi'
Provides-Extra: ionos
Requires-Dist: certbot-plugin-ionos (==0.1) ; extra == 'ionos'
Requires-Dist: ionos-api (==0.1) ; extra == 'ionos'
